pyproject.toml
py_flagsmith_cli/__init__.py
py_flagsmith_cli/__main__.py
py_flagsmith_cli/cli.py
py_flagsmith_cli/constant.py
py_flagsmith_cli/clis/get.py
py_flagsmith_cli/clis/showenv.py
py_flagsmith_cli-1.1.0.dist-info/METADATA
py_flagsmith_cli-1.1.0.dist-info/WHEEL
py_flagsmith_cli-1.1.0.dist-info/entry_points.txt
py_flagsmith_cli-1.1.0.dist-info/licenses/LICENSE
py_flagsmith_cli-1.1.0.dist-info/RECORD
