Metadata-Version: 2.4
Name: py-flagsmith-cli
Version: 1.1.0
Summary: flagsmith-cli Python Implementation.
Author-email: belingud <im.victor@qq.com>
License: MIT
License-File: LICENSE
Classifier: Programming Language :: Python :: 3
Classifier: Programming Language :: Python :: 3.8
Classifier: Programming Language :: Python :: 3.9
Classifier: Programming Language :: Python :: 3.10
Classifier: Programming Language :: Python :: 3.11
Classifier: Programming Language :: Python :: 3.12
Requires-Python: <4.0,>=3.8
Requires-Dist: python-dotenv>=1.0.1
Requires-Dist: typer>=0.16.0
